{
  "presets": [
    {
      "name": "Friday",
      "layers": [
        {
          "id": "photos_friday",
          "type": "photos",
          "name": "PHOTOS LAYER",
          "enabled": true,
          "settings": {
            "photoSourceMode": "photos",
            "imgIndices": [
              3,
              4
            ],
            "webcamIndices": [],
            "imgBlendMode": "screen"
          }
        },
        {
          "id": "particles_friday",
          "type": "particles",
          "name": "PARTICLES LAYER",
          "enabled": true,
          "settings": {
            "particleShape": "pollen",
            "useLayerColor": false,
            "layerColors": [
              "#ffffff",
              "#ffffff",
              "#ffffff",
              "#ffffff",
              "#ffffff",
              "#ffffff"
            ]
          }
        },
        {
          "id": "text_friday",
          "type": "text",
          "name": "TEXT LAYER",
          "enabled": true,
          "settings": {
            "textList": [
              "DIVENDRES TARDA",
              "AMICS",
              "TREN DE SETEMBRE",
              "AGOST",
              "LLIBERTAT"
            ],
            "textSequenceMode": "order",
            "textFontFamily": "'Inter', sans-serif",
            "textDissolveStyle": "ink",
            "textFreeze": false,
            "textManualMode": false
          }
        }
      ],
      "settings": {
        "palette": [
          "#ff5722",
          "#ffb300",
          "#e65100",
          "#5d4037",
          "#78909c",
          "#37474f"
        ],
        "physicsEnabled": true,
        "analogEnabled": true,
        "webglEnabled": false,
        "webglProjection": "3d",
        "shaderStyle": "panot",
        "horizonEnabled": true,
        "horizonStyle": "montserrat",
        "gpu_fxEnabled": false,
        "isPaused": false,
        "bgColor": "#1a120f"
      },
      "params": {
        "sensitivity": {
          "value": 2.8,
          "formula": "2.8 + bass/100",
          "useFormula": false
        },
        "trendRate": {
          "value": 0.04,
          "formula": "0.04",
          "useFormula": false
        },
        "clearOpacity": {
          "value": 0.12,
          "formula": "0.12 + (1 - trend) * 0.1",
          "useFormula": false
        },
        "analogFlash": {
          "value": 0,
          "formula": "(bass/255 > 0.85) ? (bass/255) : 0",
          "useFormula": true
        },
        "analogScratches": {
          "value": 0,
          "formula": "0",
          "useFormula": false
        },
        "analogDrift": {
          "value": 5,
          "formula": "trend > 0.8 ? 50 : 5",
          "useFormula": true
        },
        "analogScanlines": {
          "value": 0.1,
          "formula": "0.1",
          "useFormula": false
        },
        "analogNoise": {
          "value": 0.05,
          "formula": "0.05 + trend * 0.1",
          "useFormula": true
        },
        "analogWarmth": {
          "value": 0.8,
          "formula": "0.8",
          "useFormula": false
        },
        "analogLightLeak": {
          "value": 0.3,
          "formula": "0.3 + Math.sin(time/2000) * 0.2",
          "useFormula": true
        },
        "analogVignette": {
          "value": 0.4,
          "formula": "0.4",
          "useFormula": false
        },
        "opticsFocusPull": {
          "value": 30,
          "formula": "(1.0 - trend) * 40",
          "useFormula": true
        },
        "analogInkBleed": {
          "value": 0,
          "formula": "0.5",
          "useFormula": false
        },
        "analogPaperGrain": {
          "value": 0.1,
          "formula": "0.1",
          "useFormula": false
        },
        "analogStainIntensity": {
          "value": 0,
          "formula": "0",
          "useFormula": false
        },
        "imgScale_photos_friday": {
          "value": 1.2,
          "formula": "1.6 + trend*0.5",
          "useFormula": false
        },
        "imgOpacity_photos_friday": {
          "value": 0.3,
          "formula": "0.2 + trend*0.5",
          "useFormula": true
        },
        "imgGlitch_photos_friday": {
          "value": 0,
          "formula": "120 + bass",
          "useFormula": false
        },
        "imgBlur_photos_friday": {
          "value": 20,
          "formula": "10 + (1 - trend)*30 + Math.sin(time/5000)*10",
          "useFormula": true
        },
        "imgSaturate_photos_friday": {
          "value": 150,
          "formula": "100 + trend*200",
          "useFormula": true
        },
        "photoRotation_photos_friday": {
          "value": 0,
          "formula": "Math.sin(time/4000) * 0.05",
          "useFormula": true
        },
        "photoContrast_photos_friday": {
          "value": 110,
          "formula": "100 + bass",
          "useFormula": false
        },
        "particleCount_particles_friday": {
          "value": 150,
          "formula": "150 + trend*300",
          "useFormula": true
        },
        "particleSize_particles_friday": {
          "value": 42.4,
          "formula": "3 + (bass/255)*8*trend",
          "useFormula": false
        },
        "particleSpeed_particles_friday": {
          "value": 2.0,
          "formula": "2.0 + trend*4.0",
          "useFormula": true
        },
        "particleChaos_particles_friday": {
          "value": 10,
          "formula": "60 + bass",
          "useFormula": false
        },
        "particleOpacity_particles_friday": {
          "value": 0.05,
          "formula": "0.2 + trend*0.5",
          "useFormula": false
        },
        "particleDirection_particles_friday": {
          "value": 2.8,
          "formula": "2.8",
          "useFormula": false
        },
        "particleColorSpeed_particles_friday": {
          "value": 27,
          "formula": "10 + trend*50",
          "useFormula": false
        },
        "particleRotation_particles_friday": {
          "value": 0,
          "formula": "time/1000",
          "useFormula": false
        },
        "particleGravity_particles_friday": {
          "value": 0,
          "formula": "trend > 0.8 ? -2 : 1",
          "useFormula": false
        },
        "particleWind_particles_friday": {
          "value": 5,
          "formula": "5.0 + Math.sin(time/3000)*5.0",
          "useFormula": true
        },
        "particleBreezeStrength_particles_friday": {
          "value": 0.78,
          "formula": "0.5",
          "useFormula": false
        },
        "textScale_text_friday": {
          "value": 2.1,
          "formula": "1.0 + trend",
          "useFormula": false
        },
        "textBlur_text_friday": {
          "value": 23,
          "formula": "30 + (1-trend)*20",
          "useFormula": false
        },
        "textJitterX_text_friday": {
          "value": 0,
          "formula": "Math.sin(time/200) * trend * 20",
          "useFormula": true
        },
        "textJitterY_text_friday": {
          "value": 0,
          "formula": "Math.cos(time/200) * trend * 20",
          "useFormula": true
        },
        "textRotation_text_friday": {
          "value": 0,
          "formula": "Math.sin(time/1000) * 0.1",
          "useFormula": false
        },
        "textOpacity_text_friday": {
          "value": 0.45,
          "formula": "0.4 + trend*0.6",
          "useFormula": false
        },
        "textHoldTime_text_friday": {
          "value": 5,
          "formula": "5",
          "useFormula": false
        },
        "textFadeTime_text_friday": {
          "value": 1,
          "formula": "1",
          "useFormula": false
        },
        "textTypeSpeed_text_friday": {
          "value": 60,
          "formula": "60",
          "useFormula": false
        },
        "textEnvironmentDrift_text_friday": {
          "value": 0,
          "formula": "0.2 + trend",
          "useFormula": true
        },
        "textInkResolve_text_friday": {
          "value": 0.5,
          "formula": "0.5",
          "useFormula": false
        },
        "textGlow_text_friday": {
          "value": 5,
          "formula": "0",
          "useFormula": false
        }
      }
    },
    {
      "name": "Gravel",
      "layers": [
        {
          "id": "photos_gravel",
          "type": "photos",
          "name": "PHOTOS LAYER",
          "enabled": true,
          "settings": {
            "photoSourceMode": "photos",
            "imgIndices": [
              0,
              3
            ],
            "webcamIndices": [],
            "imgBlendMode": "multiply"
          }
        },
        {
          "id": "particles_gravel",
          "type": "particles",
          "name": "PARTICLES LAYER",
          "enabled": true,
          "settings": {
            "particleShape": "mote",
            "useLayerColor": false,
            "layerColors": [
              "#ffffff",
              "#ffffff",
              "#ffffff",
              "#ffffff",
              "#ffffff",
              "#ffffff"
            ]
          }
        }
      ],
      "settings": {
        "palette": [
          "#8d6e63",
          "#4caf50",
          "#2e7d32",
          "#03a9f4",
          "#80d8ff",
          "#d7ccc8"
        ],
        "physicsEnabled": true,
        "analogEnabled": true,
        "webglEnabled": false,
        "webglProjection": "3d",
        "shaderStyle": "panot",
        "horizonEnabled": true,
        "horizonStyle": "montserrat",
        "gpu_fxEnabled": true,
        "bgColor": "#100c0a"
      },
      "params": {
        "sensitivity": {
          "value": 2.8,
          "formula": "2.8 + bass/100",
          "useFormula": false
        },
        "trendRate": {
          "value": 0.04,
          "formula": "0.04",
          "useFormula": false
        },
        "clearOpacity": {
          "value": 0.12,
          "formula": "0.12 + (1 - trend) * 0.1",
          "useFormula": false
        },
        "analogFlash": {
          "value": 0,
          "formula": "0",
          "useFormula": false
        },
        "analogScratches": {
          "value": 0.2,
          "formula": "0.2",
          "useFormula": false
        },
        "analogDrift": {
          "value": 2,
          "formula": "trend > 0.8 ? 20 : 2",
          "useFormula": true
        },
        "analogScanlines": {
          "value": 0.15,
          "formula": "0.15",
          "useFormula": false
        },
        "analogNoise": {
          "value": 0.1,
          "formula": "0.1 + (bass/255)*0.2",
          "useFormula": true
        },
        "analogWarmth": {
          "value": 0.3,
          "formula": "0.3",
          "useFormula": false
        },
        "analogLightLeak": {
          "value": 0.85,
          "formula": "0.4 + (trend * 0.3)",
          "useFormula": false
        },
        "analogVignette": {
          "value": 0.45,
          "formula": "0.5",
          "useFormula": false
        },
        "opticsFocusPull": {
          "value": 30,
          "formula": "(1.0 - trend) * 50",
          "useFormula": false
        },
        "analogInkBleed": {
          "value": 1.3,
          "formula": "1.3",
          "useFormula": false
        },
        "analogPaperGrain": {
          "value": 0.15,
          "formula": "0.15",
          "useFormula": false
        },
        "analogStainIntensity": {
          "value": 0.3,
          "formula": "0.3",
          "useFormula": false
        },
        "imgScale_photos_gravel": {
          "value": 1.2,
          "formula": "1.2 + trend*0.4",
          "useFormula": true
        },
        "imgOpacity_photos_gravel": {
          "value": 0.5,
          "formula": "0.4 + trend*0.3",
          "useFormula": true
        },
        "imgGlitch_photos_gravel": {
          "value": 0,
          "formula": "bass/8",
          "useFormula": true
        },
        "imgBlur_photos_gravel": {
          "value": 15,
          "formula": "15 - trend*10",
          "useFormula": true
        },
        "imgSaturate_photos_gravel": {
          "value": 150,
          "formula": "100 + trend*200",
          "useFormula": true
        },
        "photoRotation_photos_gravel": {
          "value": 0,
          "formula": "Math.sin(time/2000) * 0.2",
          "useFormula": false
        },
        "photoContrast_photos_gravel": {
          "value": 160,
          "formula": "100 + bass",
          "useFormula": false
        },
        "particleCount_particles_gravel": {
          "value": 600,
          "formula": "600 + trend*800",
          "useFormula": true
        },
        "particleSize_particles_gravel": {
          "value": 2.0,
          "formula": "2.0 + trend*4.0",
          "useFormula": true
        },
        "particleSpeed_particles_gravel": {
          "value": 4.0,
          "formula": "4.0 + trend*6.0",
          "useFormula": true
        },
        "particleChaos_particles_gravel": {
          "value": 60,
          "formula": "60 + bass",
          "useFormula": false
        },
        "particleOpacity_particles_gravel": {
          "value": 0.4,
          "formula": "0.2 + trend*0.5",
          "useFormula": false
        },
        "particleDirection_particles_gravel": {
          "value": 0,
          "formula": "Math.atan2(y - window.innerHeight/2, x - window.innerWidth/2)",
          "useFormula": true
        },
        "particleColorSpeed_particles_gravel": {
          "value": 10,
          "formula": "10",
          "useFormula": false
        },
        "particleRotation_particles_gravel": {
          "value": 0,
          "formula": "time/1000",
          "useFormula": false
        },
        "particleGravity_particles_gravel": {
          "value": -0.2,
          "formula": "-0.2",
          "useFormula": false
        },
        "particleWind_particles_gravel": {
          "value": 15,
          "formula": "15.0 + Math.sin(time/1000)*5.0",
          "useFormula": true
        },
        "particleBreezeStrength_particles_gravel": {
          "value": 0.5,
          "formula": "0.5",
          "useFormula": false
        }
      }
    },
    {
      "name": "Rain",
      "layers": [
        {
          "id": "particles_rain",
          "type": "particles",
          "name": "PARTICLES LAYER",
          "enabled": true,
          "settings": {
            "particleShape": "circle",
            "useLayerColor": false,
            "layerColors": [
              "#ffffff",
              "#ffffff",
              "#ffffff",
              "#ffffff",
              "#ffffff",
              "#ffffff"
            ]
          }
        },
        {
          "id": "waves_rain",
          "type": "waves",
          "name": "WAVES LAYER",
          "enabled": true,
          "settings": {
            "useLayerColor": false,
            "layerColors": [
              "#ffffff",
              "#ffffff",
              "#ffffff",
              "#ffffff",
              "#ffffff",
              "#ffffff"
            ]
          }
        },
        {
          "id": "text_rain",
          "type": "text",
          "name": "TEXT LAYER",
          "enabled": true,
          "settings": {
            "textList": [
              "PLUJA AL CARRER",
              "N\u00daVOLS GRISOS",
              "EL FRED I EL VENT",
              "DINS EL MEU PETS",
              "PLUJA"
            ],
            "textSequenceMode": "order",
            "textFontFamily": "'Courier New', monospace",
            "textDissolveStyle": "ink",
            "textFreeze": false,
            "textManualMode": false
          }
        }
      ],
      "settings": {
        "palette": [
          "#1a237e",
          "#3f51b5",
          "#607d8b",
          "#00e5ff",
          "#e040fb",
          "#ffffff"
        ],
        "physicsEnabled": true,
        "analogEnabled": false,
        "webglEnabled": false,
        "webglProjection": "3d",
        "shaderStyle": "panot",
        "horizonEnabled": true,
        "horizonStyle": "montserrat",
        "gpu_fxEnabled": true,
        "bgColor": "#050710"
      },
      "params": {
        "sensitivity": {
          "value": 2.8,
          "formula": "2.8 + bass/100",
          "useFormula": false
        },
        "trendRate": {
          "value": 0.04,
          "formula": "0.04",
          "useFormula": false
        },
        "clearOpacity": {
          "value": 0.12,
          "formula": "0.12 + (1 - trend) * 0.1",
          "useFormula": false
        },
        "gpuAberration": {
          "value": 0.05,
          "formula": "0.04 + trend * 0.08",
          "useFormula": true
        },
        "gpuSmearRatio": {
          "value": 0.7,
          "formula": "0.7",
          "useFormula": false
        },
        "gpuMeltSpeed": {
          "value": 0.008,
          "formula": "0.008",
          "useFormula": false
        },
        "gpuKaleidoSegments": {
          "value": 0,
          "formula": "0",
          "useFormula": false
        },
        "gpuKaleidoRot": {
          "value": 0,
          "formula": "0",
          "useFormula": false
        },
        "particleCount_particles_rain": {
          "value": 400,
          "formula": "400 + trend*600",
          "useFormula": true
        },
        "particleSize_particles_rain": {
          "value": 1.5,
          "formula": "1.5 + trend*3.0",
          "useFormula": true
        },
        "particleSpeed_particles_rain": {
          "value": 10.0,
          "formula": "10.0 + trend*5.0",
          "useFormula": true
        },
        "particleChaos_particles_rain": {
          "value": 60,
          "formula": "60",
          "useFormula": false
        },
        "particleOpacity_particles_rain": {
          "value": 0.3,
          "formula": "0.3 + trend*0.5",
          "useFormula": true
        },
        "particleDirection_particles_rain": {
          "value": 1.57,
          "formula": "Math.PI/2 + (Math.sin(time/4000) * 0.1)",
          "useFormula": true
        },
        "particleColorSpeed_particles_rain": {
          "value": 10,
          "formula": "10",
          "useFormula": false
        },
        "particleRotation_particles_rain": {
          "value": 0,
          "formula": "time/1000",
          "useFormula": false
        },
        "particleGravity_particles_rain": {
          "value": 8.0,
          "formula": "8.0 + trend * 4.0",
          "useFormula": true
        },
        "particleWind_particles_rain": {
          "value": 2,
          "formula": "2",
          "useFormula": false
        },
        "particleBreezeStrength_particles_rain": {
          "value": 0.5,
          "formula": "0.5",
          "useFormula": false
        },
        "waveCount_waves_rain": {
          "value": 3,
          "formula": "3 + Math.floor(trend*8)",
          "useFormula": true
        },
        "waveSpeed_waves_rain": {
          "value": 1.5,
          "formula": "1.5 + trend*2.0",
          "useFormula": true
        },
        "waveThickness_waves_rain": {
          "value": 10,
          "formula": "1.5 + bass/50",
          "useFormula": true
        },
        "waveChaos_waves_rain": {
          "value": 20,
          "formula": "5.0 + Math.sin(time/1000)*20.0",
          "useFormula": true
        },
        "waveOpacity_waves_rain": {
          "value": 0.4,
          "formula": "0.4 + trend*0.4",
          "useFormula": true
        },
        "textScale_text_rain": {
          "value": 1,
          "formula": "1.0 + trend * 0.4",
          "useFormula": true
        },
        "textBlur_text_rain": {
          "value": 5,
          "formula": "5 - trend*5",
          "useFormula": true
        },
        "textJitterX_text_rain": {
          "value": 0,
          "formula": "Math.sin(time/200) * trend * 30",
          "useFormula": true
        },
        "textJitterY_text_rain": {
          "value": 0,
          "formula": "Math.cos(time/200) * trend * 30",
          "useFormula": true
        },
        "textRotation_text_rain": {
          "value": 0,
          "formula": "Math.sin(time/1000) * 0.1",
          "useFormula": false
        },
        "textOpacity_text_rain": {
          "value": 0.7,
          "formula": "0.6 + trend*0.4",
          "useFormula": true
        },
        "textHoldTime_text_rain": {
          "value": 5,
          "formula": "5",
          "useFormula": false
        },
        "textFadeTime_text_rain": {
          "value": 1,
          "formula": "1",
          "useFormula": false
        },
        "textTypeSpeed_text_rain": {
          "value": 60,
          "formula": "60",
          "useFormula": false
        },
        "textEnvironmentDrift_text_rain": {
          "value": 0.2,
          "formula": "0.2",
          "useFormula": false
        },
        "textInkResolve_text_rain": {
          "value": 0.5,
          "formula": "0.5",
          "useFormula": false
        },
        "textGlow_text_rain": {
          "value": 0,
          "formula": "0",
          "useFormula": false
        }
      }
    },
    {
      "name": "Summer",
      "layers": [
        {
          "id": "waves_summer",
          "type": "waves",
          "name": "WAVES LAYER",
          "enabled": true,
          "settings": {
            "useLayerColor": false,
            "layerColors": [
              "#ffffff",
              "#ffffff",
              "#ffffff",
              "#ffffff",
              "#ffffff",
              "#ffffff"
            ]
          }
        },
        {
          "id": "text_summer",
          "type": "text",
          "name": "TEXT LAYER",
          "enabled": true,
          "settings": {
            "textList": [
              "ESTIU",
              "ARA ARRIBA",
              "EN ELS TEUS BRA\u00c7OS",
              "VULL REFUGIAR-ME",
              "SOL I PLATJA"
            ],
            "textSequenceMode": "order",
            "textFontFamily": "Lora",
            "textDissolveStyle": "ink",
            "textFreeze": false,
            "textManualMode": false
          }
        }
      ],
      "settings": {
        "palette": [
          "#ffd600",
          "#00e5ff",
          "#00838f",
          "#7c4dff",
          "#d500f9",
          "#ff1744"
        ],
        "physicsEnabled": true,
        "analogEnabled": true,
        "webglEnabled": true,
        "webglProjection": "3d",
        "shaderStyle": "panot",
        "horizonEnabled": true,
        "horizonStyle": "montserrat",
        "gpu_fxEnabled": false,
        "bgColor": "#1a0808"
      },
      "params": {
        "sensitivity": {
          "value": 2.8,
          "formula": "2.8 + bass/100",
          "useFormula": false
        },
        "trendRate": {
          "value": 0.04,
          "formula": "0.04",
          "useFormula": false
        },
        "clearOpacity": {
          "value": 0.12,
          "formula": "0.12 + (1 - trend) * 0.1",
          "useFormula": false
        },
        "analogFlash": {
          "value": 0,
          "formula": "(bass/255 > 0.85) ? (bass/255) : 0",
          "useFormula": true
        },
        "analogScratches": {
          "value": 0,
          "formula": "0",
          "useFormula": false
        },
        "analogDrift": {
          "value": 0,
          "formula": "trend > 0.8 ? 50 : 5",
          "useFormula": false
        },
        "analogScanlines": {
          "value": 0,
          "formula": "0.15",
          "useFormula": false
        },
        "analogNoise": {
          "value": 0,
          "formula": "0.08",
          "useFormula": false
        },
        "analogWarmth": {
          "value": 0.9,
          "formula": "0.9",
          "useFormula": false
        },
        "analogLightLeak": {
          "value": 0.5,
          "formula": "0.5 + Math.sin(time/3000)*0.5",
          "useFormula": true
        },
        "analogVignette": {
          "value": 0.4,
          "formula": "0.4 + trend * 0.3",
          "useFormula": true
        },
        "opticsFocusPull": {
          "value": 0,
          "formula": "(1.0 - trend) * 50",
          "useFormula": false
        },
        "analogInkBleed": {
          "value": 1,
          "formula": "1",
          "useFormula": false
        },
        "analogPaperGrain": {
          "value": 0,
          "formula": "0.15",
          "useFormula": false
        },
        "analogStainIntensity": {
          "value": 0.2,
          "formula": "0.2 + (trend * 0.3)",
          "useFormula": true
        },
        "webglSpeed": {
          "value": 6.0,
          "formula": "6.0 + trend*8.0",
          "useFormula": true
        },
        "webglElevation": {
          "value": 1,
          "formula": "1.0",
          "useFormula": false
        },
        "webglGlow": {
          "value": 0.5,
          "formula": "0.5 + trend*1.5",
          "useFormula": true
        },
        "webglDistortion": {
          "value": 1.0,
          "formula": "1.0 + Math.sin(time/3000)*2.0",
          "useFormula": true
        },
        "panotScale": {
          "value": 5,
          "formula": "5",
          "useFormula": false
        },
        "panotBloom": {
          "value": 0.5,
          "formula": "0.5 + bass",
          "useFormula": true
        },
        "panotRotation": {
          "value": 0,
          "formula": "time / 10",
          "useFormula": true
        },
        "panotMortar": {
          "value": 0.04,
          "formula": "0.04",
          "useFormula": false
        },
        "panotThickness": {
          "value": 0.04,
          "formula": "0.04",
          "useFormula": false
        },
        "panotRoundness": {
          "value": 0.02,
          "formula": "0.02",
          "useFormula": false
        },
        "panotShadow": {
          "value": 0.3,
          "formula": "0.3",
          "useFormula": false
        },
        "horizonSpeed": {
          "value": 0.5,
          "formula": "0.5",
          "useFormula": false
        },
        "horizonComplexity": {
          "value": 5,
          "formula": "5",
          "useFormula": false
        },
        "waveCount_waves_summer": {
          "value": 2,
          "formula": "2 + Math.floor(trend*6)",
          "useFormula": true
        },
        "waveSpeed_waves_summer": {
          "value": 1.0,
          "formula": "1.0 + Math.sin(time/2000)*2.0",
          "useFormula": true
        },
        "waveThickness_waves_summer": {
          "value": 4.0,
          "formula": "4.0 + trend*8.0",
          "useFormula": true
        },
        "waveChaos_waves_summer": {
          "value": 10.0,
          "formula": "10.0 + trend*40.0",
          "useFormula": true
        },
        "waveOpacity_waves_summer": {
          "value": 0.3,
          "formula": "0.3 + trend*0.4",
          "useFormula": true
        },
        "textScale_text_summer": {
          "value": 1.2,
          "formula": "1.2 + trend * 0.5",
          "useFormula": true
        },
        "textBlur_text_summer": {
          "value": 30,
          "formula": "15 * (1 - trend)",
          "useFormula": true
        },
        "textJitterX_text_summer": {
          "value": 0,
          "formula": "Math.sin(time/200) * trend * 30",
          "useFormula": true
        },
        "textJitterY_text_summer": {
          "value": 0,
          "formula": "Math.cos(time/200) * trend * 30",
          "useFormula": true
        },
        "textRotation_text_summer": {
          "value": 0,
          "formula": "Math.sin(time/1000) * 0.1",
          "useFormula": false
        },
        "textOpacity_text_summer": {
          "value": 0.4,
          "formula": "0.7 + trend*0.3",
          "useFormula": true
        },
        "textHoldTime_text_summer": {
          "value": 5,
          "formula": "5",
          "useFormula": false
        },
        "textFadeTime_text_summer": {
          "value": 1,
          "formula": "1",
          "useFormula": false
        },
        "textTypeSpeed_text_summer": {
          "value": 60,
          "formula": "60",
          "useFormula": false
        },
        "textEnvironmentDrift_text_summer": {
          "value": 0.2,
          "formula": "0.2 + trend",
          "useFormula": true
        },
        "textInkResolve_text_summer": {
          "value": 0.5,
          "formula": "0.5",
          "useFormula": false
        },
        "textGlow_text_summer": {
          "value": 0,
          "formula": "0",
          "useFormula": false
        }
      }
    },
    {
      "name": "Nothing",
      "layers": [
        {
          "id": "rays_nothing",
          "type": "rays",
          "name": "RAYS LAYER",
          "enabled": true,
          "settings": {
            "useLayerColor": false,
            "layerColors": [
              "#ffffff",
              "#ffffff",
              "#ffffff",
              "#ffffff",
              "#ffffff",
              "#ffffff"
            ]
          }
        },
        {
          "id": "text_nothing",
          "type": "text",
          "name": "TEXT LAYER",
          "enabled": true,
          "settings": {
            "textList": [
              "RES",
              "JA NO QUEDA TEMPS",
              "MARXO EN DOS DIES",
              "AMOR",
              "REMINISC\u00c8NCIA"
            ],
            "textSequenceMode": "order",
            "textFontFamily": "Lora",
            "textDissolveStyle": "ink",
            "textFreeze": false,
            "textManualMode": false
          }
        }
      ],
      "settings": {
        "palette": [
          "#000000",
          "#1a0000",
          "#b71c1c",
          "#4a148c",
          "#880e4f",
          "#e91e63"
        ],
        "physicsEnabled": true,
        "analogEnabled": true,
        "webglEnabled": false,
        "webglProjection": "3d",
        "shaderStyle": "panot",
        "horizonEnabled": true,
        "horizonStyle": "montserrat",
        "gpu_fxEnabled": true,
        "bgColor": "#000000"
      },
      "params": {
        "sensitivity": {
          "value": 2.8,
          "formula": "2.8 + bass/100",
          "useFormula": false
        },
        "trendRate": {
          "value": 0.04,
          "formula": "0.04",
          "useFormula": false
        },
        "clearOpacity": {
          "value": 0.12,
          "formula": "0.12 + (1 - trend) * 0.1",
          "useFormula": false
        },
        "analogFlash": {
          "value": 0,
          "formula": "0",
          "useFormula": false
        },
        "analogScratches": {
          "value": 0,
          "formula": "0",
          "useFormula": false
        },
        "analogDrift": {
          "value": 0,
          "formula": "0",
          "useFormula": false
        },
        "analogScanlines": {
          "value": 0,
          "formula": "0",
          "useFormula": false
        },
        "analogNoise": {
          "value": 0.05,
          "formula": "0.05",
          "useFormula": false
        },
        "analogWarmth": {
          "value": 0.4,
          "formula": "0.4",
          "useFormula": false
        },
        "analogLightLeak": {
          "value": 0.7,
          "formula": "0.7",
          "useFormula": false
        },
        "analogVignette": {
          "value": 0.5,
          "formula": "0.5",
          "useFormula": false
        },
        "opticsFocusPull": {
          "value": 0,
          "formula": "0",
          "useFormula": false
        },
        "analogInkBleed": {
          "value": 0,
          "formula": "0",
          "useFormula": false
        },
        "analogPaperGrain": {
          "value": 0,
          "formula": "0",
          "useFormula": false
        },
        "analogStainIntensity": {
          "value": 0,
          "formula": "0",
          "useFormula": false
        },
        "gpuAberration": {
          "value": 0.05,
          "formula": "0.05 + trend * 0.15",
          "useFormula": true
        },
        "gpuSmearRatio": {
          "value": 0.95,
          "formula": "0.95",
          "useFormula": false
        },
        "gpuMeltSpeed": {
          "value": -0.003,
          "formula": "-0.003",
          "useFormula": false
        },
        "gpuKaleidoSegments": {
          "value": 0,
          "formula": "trend > 0.85 ? 4 : 0",
          "useFormula": true
        },
        "gpuKaleidoRot": {
          "value": 0,
          "formula": "(time/1000) * 0.2",
          "useFormula": true
        },
        "rayCount_rays_nothing": {
          "value": 15,
          "formula": "15 + Math.floor(trend*30)",
          "useFormula": true
        },
        "raySpeed_rays_nothing": {
          "value": 0.2,
          "formula": "0.2 + Math.sin(time/10000)*0.8",
          "useFormula": true
        },
        "rayThickness_rays_nothing": {
          "value": 8.0,
          "formula": "8.0 + bass/10.0",
          "useFormula": true
        },
        "rayCenterHole_rays_nothing": {
          "value": 50.0,
          "formula": "50.0 + trend*200.0",
          "useFormula": true
        },
        "rayChaos_rays_nothing": {
          "value": 0.4,
          "formula": "0.4 + trend*1.2",
          "useFormula": true
        },
        "rayOpacity_rays_nothing": {
          "value": 0.2,
          "formula": "0.2 + trend*0.6",
          "useFormula": true
        },
        "textScale_text_nothing": {
          "value": 1.1,
          "formula": "1.1 + trend*0.4",
          "useFormula": true
        },
        "textBlur_text_nothing": {
          "value": 30,
          "formula": "30 + (1-trend)*20",
          "useFormula": false
        },
        "textJitterX_text_nothing": {
          "value": 50,
          "formula": "Math.sin(time/500) * trend * 40",
          "useFormula": true
        },
        "textJitterY_text_nothing": {
          "value": 0,
          "formula": "Math.cos(time/500) * trend * 40",
          "useFormula": true
        },
        "textRotation_text_nothing": {
          "value": 0,
          "formula": "Math.sin(time/1000) * 0.1",
          "useFormula": false
        },
        "textOpacity_text_nothing": {
          "value": 0.4,
          "formula": "0.5 + trend*0.5",
          "useFormula": true
        },
        "textHoldTime_text_nothing": {
          "value": 5,
          "formula": "5",
          "useFormula": false
        },
        "textFadeTime_text_nothing": {
          "value": 1,
          "formula": "1",
          "useFormula": false
        },
        "textTypeSpeed_text_nothing": {
          "value": 60,
          "formula": "60",
          "useFormula": false
        },
        "textEnvironmentDrift_text_nothing": {
          "value": 0.2,
          "formula": "0.2 + trend",
          "useFormula": true
        },
        "textInkResolve_text_nothing": {
          "value": 0.5,
          "formula": "0.5",
          "useFormula": false
        },
        "textGlow_text_nothing": {
          "value": 0,
          "formula": "0",
          "useFormula": false
        }
      }
    },
    {
      "name": "Us",
      "layers": [
        {
          "id": "photos_us",
          "type": "photos",
          "name": "PHOTOS LAYER",
          "enabled": true,
          "settings": {
            "photoSourceMode": "photos",
            "imgIndices": [
              2,
              4
            ],
            "webcamIndices": [],
            "imgBlendMode": "screen"
          }
        },
        {
          "id": "particles_us",
          "type": "particles",
          "name": "PARTICLES LAYER",
          "enabled": true,
          "settings": {
            "particleShape": "petal",
            "useLayerColor": false,
            "layerColors": [
              "#ffffff",
              "#ffffff",
              "#ffffff",
              "#ffffff",
              "#ffffff",
              "#ffffff"
            ]
          }
        },
        {
          "id": "text_us",
          "type": "text",
          "name": "TEXT LAYER",
          "enabled": true,
          "settings": {
            "textList": [
              "NOSALTRES",
              "CAM\u00cd DE RETORN",
              "A GATZARA",
              "AMOR DOL\u00c7",
              "CREIXEREM"
            ],
            "textSequenceMode": "order",
            "textFontFamily": "Lora",
            "textDissolveStyle": "ink",
            "textFreeze": false,
            "textManualMode": false
          }
        }
      ],
      "settings": {
        "palette": [
          "#d7ccc8",
          "#f4b393",
          "#e0a96d",
          "#a87c53",
          "#8d6e63",
          "#ffcc80"
        ],
        "physicsEnabled": true,
        "analogEnabled": true,
        "webglEnabled": false,
        "webglProjection": "3d",
        "shaderStyle": "panot",
        "horizonEnabled": true,
        "horizonStyle": "montserrat",
        "gpu_fxEnabled": false,
        "bgColor": "#1a120f"
      },
      "params": {
        "sensitivity": {
          "value": 2.8,
          "formula": "2.8 + bass/100",
          "useFormula": false
        },
        "trendRate": {
          "value": 0.04,
          "formula": "0.04",
          "useFormula": false
        },
        "clearOpacity": {
          "value": 0.12,
          "formula": "0.12 + (1 - trend) * 0.1",
          "useFormula": false
        },
        "analogFlash": {
          "value": 0,
          "formula": "0",
          "useFormula": false
        },
        "analogScratches": {
          "value": 0,
          "formula": "0",
          "useFormula": false
        },
        "analogDrift": {
          "value": 5,
          "formula": "5",
          "useFormula": false
        },
        "analogScanlines": {
          "value": 0.05,
          "formula": "0.05",
          "useFormula": false
        },
        "analogNoise": {
          "value": 0.1,
          "formula": "0.1",
          "useFormula": false
        },
        "analogWarmth": {
          "value": 0.7,
          "formula": "0.7",
          "useFormula": false
        },
        "analogLightLeak": {
          "value": 0.4,
          "formula": "0.4",
          "useFormula": false
        },
        "analogVignette": {
          "value": 0.5,
          "formula": "0.5",
          "useFormula": false
        },
        "opticsFocusPull": {
          "value": 60,
          "formula": "60 + Math.sin(time/8000)*40",
          "useFormula": true
        },
        "analogInkBleed": {
          "value": 1,
          "formula": "1",
          "useFormula": false
        },
        "analogPaperGrain": {
          "value": 0.2,
          "formula": "0.2",
          "useFormula": false
        },
        "analogStainIntensity": {
          "value": 0.4,
          "formula": "0.4",
          "useFormula": false
        },
        "imgScale_photos_us": {
          "value": 1.1,
          "formula": "1.1 + Math.sin(time/10000)*0.1",
          "useFormula": true
        },
        "imgOpacity_photos_us": {
          "value": 0.15,
          "formula": "0.15 + trend*0.25",
          "useFormula": true
        },
        "imgGlitch_photos_us": {
          "value": 0,
          "formula": "120",
          "useFormula": false
        },
        "imgBlur_photos_us": {
          "value": 40,
          "formula": "40 + Math.sin(time/6000)*20",
          "useFormula": true
        },
        "imgSaturate_photos_us": {
          "value": 150,
          "formula": "150",
          "useFormula": false
        },
        "photoRotation_photos_us": {
          "value": 0,
          "formula": "0.1",
          "useFormula": false
        },
        "photoContrast_photos_us": {
          "value": 110,
          "formula": "110",
          "useFormula": false
        },
        "particleCount_particles_us": {
          "value": 300,
          "formula": "300 + trend*400",
          "useFormula": true
        },
        "particleSize_particles_us": {
          "value": 6.0,
          "formula": "6.0 + trend*12.0",
          "useFormula": true
        },
        "particleSpeed_particles_us": {
          "value": 1.5,
          "formula": "1.5 + trend*2.0",
          "useFormula": true
        },
        "particleChaos_particles_us": {
          "value": 15,
          "formula": "15.0 + Math.sin(time/4000)*10.0",
          "useFormula": true
        },
        "particleOpacity_particles_us": {
          "value": 0.3,
          "formula": "0.3 + trend*0.4",
          "useFormula": true
        },
        "particleDirection_particles_us": {
          "value": 0,
          "formula": "0",
          "useFormula": false
        },
        "particleColorSpeed_particles_us": {
          "value": 9,
          "formula": "9",
          "useFormula": false
        },
        "particleRotation_particles_us": {
          "value": 0,
          "formula": "time/2000",
          "useFormula": true
        },
        "particleGravity_particles_us": {
          "value": 0.8,
          "formula": "0.8 + trend*0.5",
          "useFormula": true
        },
        "particleWind_particles_us": {
          "value": -3,
          "formula": "-3.0 + Math.sin(time/5000)*2.0",
          "useFormula": true
        },
        "particleBreezeStrength_particles_us": {
          "value": 0.5,
          "formula": "0.5",
          "useFormula": false
        },
        "textScale_text_us": {
          "value": 1,
          "formula": "1.0",
          "useFormula": false
        },
        "textBlur_text_us": {
          "value": 30,
          "formula": "30",
          "useFormula": false
        },
        "textJitterX_text_us": {
          "value": 0,
          "formula": "0",
          "useFormula": false
        },
        "textJitterY_text_us": {
          "value": 0,
          "formula": "0",
          "useFormula": false
        },
        "textRotation_text_us": {
          "value": 0,
          "formula": "0",
          "useFormula": false
        },
        "textOpacity_text_us": {
          "value": 0.4,
          "formula": "0.4 + trend*0.4",
          "useFormula": true
        },
        "textHoldTime_text_us": {
          "value": 5,
          "formula": "5",
          "useFormula": false
        },
        "textFadeTime_text_us": {
          "value": 1,
          "formula": "1",
          "useFormula": false
        },
        "textTypeSpeed_text_us": {
          "value": 60,
          "formula": "60",
          "useFormula": false
        },
        "textEnvironmentDrift_text_us": {
          "value": 0.2,
          "formula": "0.2",
          "useFormula": false
        },
        "textInkResolve_text_us": {
          "value": 0.5,
          "formula": "0.5",
          "useFormula": false
        },
        "textGlow_text_us": {
          "value": 0,
          "formula": "0",
          "useFormula": false
        }
      }
    },
    {
      "name": "You",
      "layers": [
        {
          "id": "particles_you",
          "type": "particles",
          "name": "PARTICLES LAYER",
          "enabled": true,
          "settings": {
            "particleShape": "star",
            "useLayerColor": false,
            "layerColors": [
              "#ffffff",
              "#ffffff",
              "#ffffff",
              "#ffffff",
              "#ffffff",
              "#ffffff"
            ]
          }
        },
        {
          "id": "waves_you",
          "type": "waves",
          "name": "WAVES LAYER",
          "enabled": true,
          "settings": {
            "useLayerColor": false,
            "layerColors": [
              "#ffffff",
              "#ffffff",
              "#ffffff",
              "#ffffff",
              "#ffffff",
              "#ffffff"
            ]
          }
        },
        {
          "id": "rays_you",
          "type": "rays",
          "name": "RAYS LAYER",
          "enabled": true,
          "settings": {
            "useLayerColor": false,
            "layerColors": [
              "#ffffff",
              "#ffffff",
              "#ffffff",
              "#ffffff",
              "#ffffff",
              "#ffffff"
            ]
          }
        },
        {
          "id": "text_you",
          "type": "text",
          "name": "TEXT LAYER",
          "enabled": true,
          "settings": {
            "textList": [
              "NOM\u00c9S PER TU",
              "QUAN EM MIRES",
              "FIL DEL VENT",
              "INNOC\u00c8NCIA",
              "EL MIRACLE"
            ],
            "textSequenceMode": "order",
            "textFontFamily": "Lora",
            "textDissolveStyle": "ink",
            "textFreeze": false,
            "textManualMode": false
          }
        }
      ],
      "settings": {
        "palette": [
          "#ffffff",
          "#e0f7fa",
          "#b2ebf2",
          "#ffe082",
          "#fff9c4",
          "#fff59d"
        ],
        "physicsEnabled": true,
        "analogEnabled": true,
        "webglEnabled": false,
        "webglProjection": "3d",
        "shaderStyle": "panot",
        "horizonEnabled": true,
        "horizonStyle": "montserrat",
        "gpu_fxEnabled": false,
        "bgColor": "#0b0c10"
      },
      "params": {
        "sensitivity": {
          "value": 2.8,
          "formula": "2.8 + bass/100",
          "useFormula": false
        },
        "trendRate": {
          "value": 0.04,
          "formula": "0.04",
          "useFormula": false
        },
        "clearOpacity": {
          "value": 0.12,
          "formula": "0.12 + (1 - trend) * 0.1",
          "useFormula": false
        },
        "analogFlash": {
          "value": 0,
          "formula": "0",
          "useFormula": false
        },
        "analogScratches": {
          "value": 0,
          "formula": "0",
          "useFormula": false
        },
        "analogDrift": {
          "value": 0,
          "formula": "0",
          "useFormula": false
        },
        "analogScanlines": {
          "value": 0,
          "formula": "0",
          "useFormula": false
        },
        "analogNoise": {
          "value": 0,
          "formula": "0",
          "useFormula": false
        },
        "analogWarmth": {
          "value": 0.4,
          "formula": "0.4",
          "useFormula": false
        },
        "analogLightLeak": {
          "value": 0.7,
          "formula": "0.7 + Math.sin(time/4000)*0.3",
          "useFormula": true
        },
        "analogVignette": {
          "value": 0.5,
          "formula": "0.3",
          "useFormula": false
        },
        "opticsFocusPull": {
          "value": 0,
          "formula": "80 + Math.sin(time/5000)*40",
          "useFormula": true
        },
        "analogInkBleed": {
          "value": 0,
          "formula": "0",
          "useFormula": false
        },
        "analogPaperGrain": {
          "value": 0,
          "formula": "0",
          "useFormula": false
        },
        "analogStainIntensity": {
          "value": 0.25,
          "formula": "0.25",
          "useFormula": false
        },
        "imgScale": {
          "value": 1.6,
          "formula": "1.6",
          "useFormula": false
        },
        "imgOpacity": {
          "value": 0.7,
          "formula": "0.7",
          "useFormula": false
        },
        "imgGlitch": {
          "value": 120,
          "formula": "120",
          "useFormula": false
        },
        "imgBlur": {
          "value": 20,
          "formula": "20",
          "useFormula": false
        },
        "imgSaturate": {
          "value": 150,
          "formula": "150",
          "useFormula": false
        },
        "photoRotation": {
          "value": 0,
          "formula": "0",
          "useFormula": false
        },
        "photoContrast": {
          "value": 110,
          "formula": "110",
          "useFormula": false
        },
        "particleCount_particles_you": {
          "value": 400,
          "formula": "400 + trend*500",
          "useFormula": true
        },
        "particleSize_particles_you": {
          "value": 1.5,
          "formula": "1.5 + trend*4.0",
          "useFormula": true
        },
        "particleSpeed_particles_you": {
          "value": 0.4,
          "formula": "0.4 + trend*0.8",
          "useFormula": true
        },
        "particleChaos_particles_you": {
          "value": 5,
          "formula": "5.0 + trend*10.0",
          "useFormula": true
        },
        "particleOpacity_particles_you": {
          "value": 0.8,
          "formula": "0.4 + trend*0.5",
          "useFormula": true
        },
        "particleDirection_particles_you": {
          "value": 0,
          "formula": "0",
          "useFormula": false
        },
        "particleColorSpeed_particles_you": {
          "value": 10,
          "formula": "10",
          "useFormula": false
        },
        "particleRotation_particles_you": {
          "value": 0,
          "formula": "time/1000",
          "useFormula": false
        },
        "particleGravity_particles_you": {
          "value": -0.2,
          "formula": "-0.2 - trend*0.3",
          "useFormula": true
        },
        "particleWind_particles_you": {
          "value": 2,
          "formula": "Math.sin(time/6000)*2.0",
          "useFormula": true
        },
        "particleBreezeStrength_particles_you": {
          "value": 0.1,
          "formula": "0.1",
          "useFormula": false
        },
        "waveCount_waves_you": {
          "value": 2,
          "formula": "1 + Math.floor(trend*3)",
          "useFormula": true
        },
        "waveSpeed_waves_you": {
          "value": -4.4,
          "formula": "0.6 + trend*1.0",
          "useFormula": true
        },
        "waveThickness_waves_you": {
          "value": 13,
          "formula": "3.0 + trend*5.0",
          "useFormula": true
        },
        "waveChaos_waves_you": {
          "value": 20,
          "formula": "20",
          "useFormula": false
        },
        "waveOpacity_waves_you": {
          "value": 0.5,
          "formula": "0.2 + trend*0.3",
          "useFormula": true
        },
        "rayCount_rays_you": {
          "value": 13,
          "formula": "8 + Math.floor(trend*12)",
          "useFormula": true
        },
        "raySpeed_rays_you": {
          "value": 0.1,
          "formula": "0.05 + Math.sin(time/12000)*0.1",
          "useFormula": true
        },
        "rayThickness_rays_you": {
          "value": 5,
          "formula": "3.0 + trend*6.0",
          "useFormula": true
        },
        "rayCenterHole_rays_you": {
          "value": 610,
          "formula": "300.0 + Math.sin(time/8000)*150.0",
          "useFormula": true
        },
        "rayChaos_rays_you": {
          "value": 1.7,
          "formula": "1.7",
          "useFormula": false
        },
        "rayOpacity_rays_you": {
          "value": 0.9,
          "formula": "0.3 + trend*0.4",
          "useFormula": true
        },
        "textScale_text_you": {
          "value": 0.8,
          "formula": "0.8",
          "useFormula": false
        },
        "textBlur_text_you": {
          "value": 105,
          "formula": "30 + Math.sin(time/4000)*20",
          "useFormula": true
        },
        "textJitterX_text_you": {
          "value": 0,
          "formula": "Math.sin(time/200) * trend * 30",
          "useFormula": true
        },
        "textJitterY_text_you": {
          "value": 0,
          "formula": "Math.cos(time/200) * trend * 30",
          "useFormula": true
        },
        "textRotation_text_you": {
          "value": 0,
          "formula": "Math.sin(time/1000) * 0.1",
          "useFormula": false
        },
        "textOpacity_text_you": {
          "value": 0.4,
          "formula": "0.5 + trend*0.3",
          "useFormula": true
        },
        "textHoldTime_text_you": {
          "value": 5,
          "formula": "5",
          "useFormula": false
        },
        "textFadeTime_text_you": {
          "value": 1,
          "formula": "1",
          "useFormula": false
        },
        "textTypeSpeed_text_you": {
          "value": 200,
          "formula": "60",
          "useFormula": false
        },
        "textEnvironmentDrift_text_you": {
          "value": 0.2,
          "formula": "0.2",
          "useFormula": false
        },
        "textInkResolve_text_you": {
          "value": 0.34,
          "formula": "0.5",
          "useFormula": false
        },
        "textGlow_text_you": {
          "value": 0,
          "formula": "0",
          "useFormula": false
        }
      }
    },
    {
      "name": "Beach",
      "layers": [
        {
          "id": "particles_beach",
          "type": "particles",
          "name": "PARTICLES LAYER",
          "enabled": true,
          "settings": {
            "particleShape": "circle",
            "useLayerColor": false,
            "layerColors": [
              "#ffffff",
              "#ffffff",
              "#ffffff",
              "#ffffff",
              "#ffffff",
              "#ffffff"
            ]
          }
        },
        {
          "id": "text_beach",
          "type": "text",
          "name": "TEXT LAYER",
          "enabled": true,
          "settings": {
            "textList": [
              "LA PLATJA",
              "QUAN JA NO VISQUIS AQU\u00cd",
              "EL BUID",
              "AD\u00c9U",
              "COSTA D'HIVERN"
            ],
            "textSequenceMode": "order",
            "textFontFamily": "Lora",
            "textDissolveStyle": "ink",
            "textFreeze": false,
            "textManualMode": false
          }
        }
      ],
      "settings": {
        "palette": [
          "#78909c",
          "#b0bec5",
          "#cfd8dc",
          "#a3b899",
          "#809a80",
          "#ffffff"
        ],
        "physicsEnabled": true,
        "analogEnabled": true,
        "webglEnabled": true,
        "webglProjection": "3d",
        "shaderStyle": "cells",
        "horizonEnabled": true,
        "horizonStyle": "montserrat",
        "gpu_fxEnabled": false,
        "bgColor": "#101518"
      },
      "params": {
        "sensitivity": {
          "value": 2.8,
          "formula": "2.8 + bass/100",
          "useFormula": false
        },
        "trendRate": {
          "value": 0.04,
          "formula": "0.04",
          "useFormula": false
        },
        "clearOpacity": {
          "value": 0.12,
          "formula": "0.12 + (1 - trend) * 0.1",
          "useFormula": false
        },
        "analogFlash": {
          "value": 1,
          "formula": "time/180000",
          "useFormula": true
        },
        "analogScratches": {
          "value": 0.23,
          "formula": "0.23",
          "useFormula": false
        },
        "analogDrift": {
          "value": 0,
          "formula": "10 + bass/20",
          "useFormula": false
        },
        "analogScanlines": {
          "value": 0,
          "formula": "0.15",
          "useFormula": false
        },
        "analogNoise": {
          "value": 0.15,
          "formula": "0.15",
          "useFormula": false
        },
        "analogWarmth": {
          "value": 0,
          "formula": "0",
          "useFormula": false
        },
        "analogLightLeak": {
          "value": 0,
          "formula": "time/180000",
          "useFormula": false
        },
        "analogVignette": {
          "value": 0.7,
          "formula": "0.7",
          "useFormula": false
        },
        "opticsFocusPull": {
          "value": 0,
          "formula": "120 * (1 - trend)",
          "useFormula": true
        },
        "analogInkBleed": {
          "value": 0,
          "formula": "0.5 + (bass/255)*4.0",
          "useFormula": false
        },
        "analogPaperGrain": {
          "value": 0,
          "formula": "0.15",
          "useFormula": false
        },
        "analogStainIntensity": {
          "value": 0.85,
          "formula": "0.5",
          "useFormula": false
        },
        "webglSpeed": {
          "value": 1.0,
          "formula": "1.0 + trend*2.0",
          "useFormula": true
        },
        "webglElevation": {
          "value": -0.6,
          "formula": "-0.6",
          "useFormula": false
        },
        "webglGlow": {
          "value": 0.3,
          "formula": "0.3 + trend*0.7",
          "useFormula": true
        },
        "webglDistortion": {
          "value": 1,
          "formula": "0.5 + trend*1.0",
          "useFormula": true
        },
        "panotScale": {
          "value": 10,
          "formula": "5",
          "useFormula": false
        },
        "panotBloom": {
          "value": 1.85,
          "formula": "0.5 + bass",
          "useFormula": false
        },
        "panotRotation": {
          "value": 0,
          "formula": "time / 10",
          "useFormula": false
        },
        "panotMortar": {
          "value": 0.052,
          "formula": "0.04",
          "useFormula": false
        },
        "panotThickness": {
          "value": 0.025,
          "formula": "0.04",
          "useFormula": false
        },
        "panotRoundness": {
          "value": 0.026,
          "formula": "0.02",
          "useFormula": false
        },
        "panotShadow": {
          "value": 0.31,
          "formula": "0.3",
          "useFormula": false
        },
        "horizonSpeed": {
          "value": 0.68,
          "formula": "0.68",
          "useFormula": false
        },
        "horizonComplexity": {
          "value": 20,
          "formula": "15",
          "useFormula": false
        },
        "particleCount_particles_beach": {
          "value": 800,
          "formula": "800 - (time/2000)%400",
          "useFormula": true
        },
        "particleSize_particles_beach": {
          "value": 2.1,
          "formula": "1.5 + trend*3.0",
          "useFormula": true
        },
        "particleSpeed_particles_beach": {
          "value": 20,
          "formula": "0.8 + trend*1.2",
          "useFormula": true
        },
        "particleChaos_particles_beach": {
          "value": 200,
          "formula": "60 + bass",
          "useFormula": false
        },
        "particleOpacity_particles_beach": {
          "value": 1,
          "formula": "0.2 + trend*0.5",
          "useFormula": true
        },
        "particleDirection_particles_beach": {
          "value": -1.29,
          "formula": "Math.atan2(y - window.innerHeight/2, x - window.innerWidth/2)",
          "useFormula": false
        },
        "particleColorSpeed_particles_beach": {
          "value": 0,
          "formula": "10",
          "useFormula": false
        },
        "particleRotation_particles_beach": {
          "value": 0.128,
          "formula": "time/1000",
          "useFormula": false
        },
        "particleGravity_particles_beach": {
          "value": 10,
          "formula": "0.1",
          "useFormula": false
        },
        "particleWind_particles_beach": {
          "value": -11.9,
          "formula": "-4.0 - Math.sin(time/4000)*2.0",
          "useFormula": true
        },
        "particleBreezeStrength_particles_beach": {
          "value": 0.5,
          "formula": "0.5",
          "useFormula": false
        },
        "textScale_text_beach": {
          "value": 0.75,
          "formula": "0.9 + trend*0.2",
          "useFormula": true
        },
        "textBlur_text_beach": {
          "value": 6,
          "formula": "20 * (1 - trend)",
          "useFormula": true
        },
        "textJitterX_text_beach": {
          "value": 0,
          "formula": "Math.sin(time/200) * trend * 30",
          "useFormula": true
        },
        "textJitterY_text_beach": {
          "value": 0,
          "formula": "Math.sin(time/200)*trend*50",
          "useFormula": true
        },
        "textRotation_text_beach": {
          "value": 0,
          "formula": "Math.sin(time/1000) * 0.1",
          "useFormula": false
        },
        "textOpacity_text_beach": {
          "value": 0.4,
          "formula": "0.5 + trend*0.4",
          "useFormula": true
        },
        "textHoldTime_text_beach": {
          "value": 13,
          "formula": "13",
          "useFormula": false
        },
        "textFadeTime_text_beach": {
          "value": 2,
          "formula": "2",
          "useFormula": false
        },
        "textTypeSpeed_text_beach": {
          "value": 125,
          "formula": "60",
          "useFormula": false
        },
        "textEnvironmentDrift_text_beach": {
          "value": 0.25,
          "formula": "0.25",
          "useFormula": false
        },
        "textInkResolve_text_beach": {
          "value": 0.5,
          "formula": "0.5",
          "useFormula": false
        },
        "textGlow_text_beach": {
          "value": 0,
          "formula": "0",
          "useFormula": false
        }
      }
    },
    {
      "name": "Chestnut",
      "layers": [
        {
          "id": "particles_chestnut",
          "type": "particles",
          "name": "PARTICLES LAYER",
          "enabled": true,
          "settings": {
            "particleShape": "leaf",
            "useLayerColor": false,
            "layerColors": [
              "#ffffff",
              "#ffffff",
              "#ffffff",
              "#ffffff",
              "#ffffff",
              "#ffffff"
            ]
          }
        },
        {
          "id": "waves_chestnut",
          "type": "waves",
          "name": "WAVES LAYER",
          "enabled": true,
          "settings": {
            "useLayerColor": false,
            "layerColors": [
              "#ffffff",
              "#ffffff",
              "#ffffff",
              "#ffffff",
              "#ffffff",
              "#ffffff"
            ]
          }
        },
        {
          "id": "text_chestnut",
          "type": "text",
          "name": "TEXT LAYER",
          "enabled": true,
          "settings": {
            "textList": [
              "CASTANYER",
              "LES FLORS EN BLANC",
              "AMISTAT",
              "PRIMAVERA",
              "BROTS VERDS"
            ],
            "textSequenceMode": "order",
            "textFontFamily": "Lora",
            "textDissolveStyle": "ink",
            "textFreeze": false,
            "textManualMode": false
          }
        }
      ],
      "settings": {
        "palette": [
          "#81c784",
          "#c8e6c9",
          "#f8bbd0",
          "#ff80ab",
          "#fff59d",
          "#f0f4c3"
        ],
        "physicsEnabled": true,
        "analogEnabled": true,
        "webglEnabled": false,
        "webglProjection": "3d",
        "shaderStyle": "panot",
        "horizonEnabled": true,
        "horizonStyle": "montserrat",
        "gpu_fxEnabled": false,
        "bgColor": "#101812"
      },
      "params": {
        "sensitivity": {
          "value": 2.8,
          "formula": "2.8 + bass/100",
          "useFormula": false
        },
        "trendRate": {
          "value": 0.04,
          "formula": "0.04",
          "useFormula": false
        },
        "clearOpacity": {
          "value": 0.12,
          "formula": "0.12 + (1 - trend) * 0.1",
          "useFormula": false
        },
        "analogFlash": {
          "value": 0,
          "formula": "(bass/255 > 0.82) ? (bass/255) : 0",
          "useFormula": true
        },
        "analogScratches": {
          "value": 0,
          "formula": "0",
          "useFormula": false
        },
        "analogDrift": {
          "value": 0,
          "formula": "trend > 0.8 ? 50 : 5",
          "useFormula": false
        },
        "analogScanlines": {
          "value": 0,
          "formula": "0.15",
          "useFormula": false
        },
        "analogNoise": {
          "value": 0,
          "formula": "0.08",
          "useFormula": false
        },
        "analogWarmth": {
          "value": 0.6,
          "formula": "0.6",
          "useFormula": false
        },
        "analogLightLeak": {
          "value": 0.4,
          "formula": "0.4 + Math.sin(time/2000)*0.4",
          "useFormula": true
        },
        "analogVignette": {
          "value": 0.5,
          "formula": "0.5",
          "useFormula": false
        },
        "opticsFocusPull": {
          "value": 30,
          "formula": "(1.0 - trend) * 50",
          "useFormula": false
        },
        "analogInkBleed": {
          "value": 1,
          "formula": "1",
          "useFormula": false
        },
        "analogPaperGrain": {
          "value": 0.15,
          "formula": "0.15",
          "useFormula": false
        },
        "analogStainIntensity": {
          "value": 0.2,
          "formula": "0.2",
          "useFormula": false
        },
        "particleCount_particles_chestnut": {
          "value": 400,
          "formula": "400 + trend*400",
          "useFormula": true
        },
        "particleSize_particles_chestnut": {
          "value": 2.1,
          "formula": "3.0 + trend*8.0",
          "useFormula": true
        },
        "particleSpeed_particles_chestnut": {
          "value": 18.6,
          "formula": "2.0 + trend*3.0",
          "useFormula": true
        },
        "particleChaos_particles_chestnut": {
          "value": 31,
          "formula": "60 + bass",
          "useFormula": false
        },
        "particleOpacity_particles_chestnut": {
          "value": 0.4,
          "formula": "0.4 + trend*0.4",
          "useFormula": true
        },
        "particleDirection_particles_chestnut": {
          "value": 0.65,
          "formula": "Math.PI/3 + Math.sin(time/2000)*0.2",
          "useFormula": true
        },
        "particleColorSpeed_particles_chestnut": {
          "value": 30,
          "formula": "15 + trend*20",
          "useFormula": true
        },
        "particleRotation_particles_chestnut": {
          "value": 3.01,
          "formula": "time/1000",
          "useFormula": false
        },
        "particleGravity_particles_chestnut": {
          "value": 3.4,
          "formula": "1.2 + trend*0.8",
          "useFormula": true
        },
        "particleWind_particles_chestnut": {
          "value": 3,
          "formula": "3 + Math.sin(time/3000)*2",
          "useFormula": true
        },
        "particleBreezeStrength_particles_chestnut": {
          "value": 0.5,
          "formula": "0.5",
          "useFormula": false
        },
        "waveCount_waves_chestnut": {
          "value": 1,
          "formula": "1 + Math.floor(trend*5)",
          "useFormula": true
        },
        "waveSpeed_waves_chestnut": {
          "value": 1.5,
          "formula": "1.5 + trend*2.0",
          "useFormula": true
        },
        "waveThickness_waves_chestnut": {
          "value": 10,
          "formula": "2.0 + trend*6.0",
          "useFormula": true
        },
        "waveChaos_waves_chestnut": {
          "value": 20,
          "formula": "20",
          "useFormula": false
        },
        "waveOpacity_waves_chestnut": {
          "value": 0.8,
          "formula": "0.2 + trend*0.4",
          "useFormula": true
        },
        "textScale_text_chestnut": {
          "value": 1.15,
          "formula": "1.15 + trend * 0.3",
          "useFormula": true
        },
        "textBlur_text_chestnut": {
          "value": 0,
          "formula": "30 + (1-trend)*20",
          "useFormula": false
        },
        "textJitterX_text_chestnut": {
          "value": 0,
          "formula": "Math.sin(time/200) * trend * 30",
          "useFormula": true
        },
        "textJitterY_text_chestnut": {
          "value": 0,
          "formula": "Math.cos(time/200) * trend * 30",
          "useFormula": true
        },
        "textRotation_text_chestnut": {
          "value": 0,
          "formula": "Math.sin(time/1000) * 0.1",
          "useFormula": false
        },
        "textOpacity_text_chestnut": {
          "value": 0.65,
          "formula": "Math.sin(time/1000)*.2+0.5",
          "useFormula": true
        },
        "textHoldTime_text_chestnut": {
          "value": 5,
          "formula": "5",
          "useFormula": false
        },
        "textFadeTime_text_chestnut": {
          "value": 1,
          "formula": "1",
          "useFormula": false
        },
        "textTypeSpeed_text_chestnut": {
          "value": 60,
          "formula": "60",
          "useFormula": false
        },
        "textEnvironmentDrift_text_chestnut": {
          "value": 0.2,
          "formula": "0.2 + trend",
          "useFormula": true
        },
        "textInkResolve_text_chestnut": {
          "value": 0.61,
          "formula": "0.5",
          "useFormula": false
        },
        "textGlow_text_chestnut": {
          "value": 0,
          "formula": "0",
          "useFormula": false
        }
      }
    },
    {
      "name": "House",
      "layers": [
        {
          "id": "photos_house",
          "type": "photos",
          "name": "PHOTOS LAYER",
          "enabled": true,
          "settings": {
            "photoSourceMode": "photos",
            "imgIndices": [
              4
            ],
            "webcamIndices": [],
            "imgBlendMode": "screen"
          }
        },
        {
          "id": "particles_house",
          "type": "particles",
          "name": "PARTICLES LAYER",
          "enabled": true,
          "settings": {
            "particleShape": "mote",
            "useLayerColor": false,
            "layerColors": [
              "#ffffff",
              "#ffffff",
              "#ffffff",
              "#ffffff",
              "#ffffff",
              "#ffffff"
            ]
          }
        },
        {
          "id": "text_house",
          "type": "text",
          "name": "TEXT LAYER",
          "enabled": true,
          "settings": {
            "textList": [
              "CASA",
              "AMICS DE SEMPRE",
              "EL SO DE LA GUITARRA",
              "RETORN",
              "AGOST"
            ],
            "textSequenceMode": "order",
            "textFontFamily": "Lora",
            "textDissolveStyle": "ink",
            "textFreeze": false,
            "textManualMode": false
          }
        }
      ],
      "settings": {
        "palette": [
          "#bf360c",
          "#d84315",
          "#ff8a65",
          "#ffcc80",
          "#212121",
          "#000000"
        ],
        "physicsEnabled": true,
        "analogEnabled": true,
        "webglEnabled": false,
        "webglProjection": "2d",
        "shaderStyle": "grid",
        "horizonEnabled": true,
        "horizonStyle": "montserrat",
        "gpu_fxEnabled": false,
        "bgColor": "#100502"
      },
      "params": {
        "sensitivity": {
          "value": 2.8,
          "formula": "2.8 + bass/100",
          "useFormula": false
        },
        "trendRate": {
          "value": 0.04,
          "formula": "0.04",
          "useFormula": false
        },
        "clearOpacity": {
          "value": 0.12,
          "formula": "0.12 + (1 - trend) * 0.1",
          "useFormula": false
        },
        "analogFlash": {
          "value": 0,
          "formula": "(bass/255 > 0.8) ? (bass/255) : 0",
          "useFormula": false
        },
        "analogScratches": {
          "value": 0.15,
          "formula": "0.15",
          "useFormula": false
        },
        "analogDrift": {
          "value": 10,
          "formula": "10 + trend * 40",
          "useFormula": true
        },
        "analogScanlines": {
          "value": 0.05,
          "formula": "0.05",
          "useFormula": false
        },
        "analogNoise": {
          "value": 0.3,
          "formula": "0.3 + trend * 0.2",
          "useFormula": true
        },
        "analogWarmth": {
          "value": 0.95,
          "formula": "0.95",
          "useFormula": false
        },
        "analogLightLeak": {
          "value": 1,
          "formula": "1",
          "useFormula": false
        },
        "analogVignette": {
          "value": 0.6,
          "formula": "0.6",
          "useFormula": false
        },
        "opticsFocusPull": {
          "value": 0,
          "formula": "(1.0 - trend) * 50",
          "useFormula": false
        },
        "analogInkBleed": {
          "value": 0,
          "formula": "0.5 + (bass/255)*4.0",
          "useFormula": false
        },
        "analogPaperGrain": {
          "value": 0,
          "formula": "0.15",
          "useFormula": false
        },
        "analogStainIntensity": {
          "value": 0,
          "formula": "0.2 + (trend * 0.3)",
          "useFormula": false
        },
        "imgScale_photos_house": {
          "value": 1.1,
          "formula": "1.1 + trend * 0.5",
          "useFormula": true
        },
        "imgOpacity_photos_house": {
          "value": 0.7,
          "formula": "0.5 + trend*0.4",
          "useFormula": true
        },
        "imgGlitch_photos_house": {
          "value": 0,
          "formula": "trend * 50 + bass/5",
          "useFormula": true
        },
        "imgBlur_photos_house": {
          "value": 0,
          "formula": "5 - trend*5",
          "useFormula": true
        },
        "imgSaturate_photos_house": {
          "value": 0,
          "formula": "100",
          "useFormula": false
        },
        "photoRotation_photos_house": {
          "value": 0,
          "formula": "Math.sin(time/2000) * 0.2",
          "useFormula": false
        },
        "photoContrast_photos_house": {
          "value": 85,
          "formula": "120 + trend*80",
          "useFormula": true
        },
        "particleCount_particles_house": {
          "value": 300,
          "formula": "300 + trend*400",
          "useFormula": true
        },
        "particleSize_particles_house": {
          "value": 1.0,
          "formula": "1.0 + trend*3.0",
          "useFormula": true
        },
        "particleSpeed_particles_house": {
          "value": 2,
          "formula": "0.5 + trend*1.5",
          "useFormula": true
        },
        "particleChaos_particles_house": {
          "value": 60,
          "formula": "60 + bass",
          "useFormula": false
        },
        "particleOpacity_particles_house": {
          "value": 0.4,
          "formula": "0.2 + trend*0.4",
          "useFormula": true
        },
        "particleDirection_particles_house": {
          "value": 0,
          "formula": "Math.atan2(y - window.innerHeight/2, x - window.innerWidth/2)",
          "useFormula": true
        },
        "particleColorSpeed_particles_house": {
          "value": 10,
          "formula": "10",
          "useFormula": false
        },
        "particleRotation_particles_house": {
          "value": 0,
          "formula": "time/1000",
          "useFormula": false
        },
        "particleGravity_particles_house": {
          "value": 0,
          "formula": "trend > 0.8 ? -2 : 1",
          "useFormula": false
        },
        "particleWind_particles_house": {
          "value": 2,
          "formula": "2.0 + (trend * 10)",
          "useFormula": true
        },
        "particleBreezeStrength_particles_house": {
          "value": 0.5,
          "formula": "0.5",
          "useFormula": false
        },
        "textScale_text_house": {
          "value": 1.5,
          "formula": "1.4 + trend*0.4",
          "useFormula": true
        },
        "textBlur_text_house": {
          "value": 0,
          "formula": "1 + 40 * Math.pow(Math.E, -0.00001155 * time)",
          "useFormula": true
        },
        "textJitterX_text_house": {
          "value": 0,
          "formula": "Math.sin(time/200) * trend * 30",
          "useFormula": false
        },
        "textJitterY_text_house": {
          "value": 0,
          "formula": "Math.cos(time/200) * trend * 30",
          "useFormula": false
        },
        "textRotation_text_house": {
          "value": 0,
          "formula": "Math.sin(time/1000) * 0.1",
          "useFormula": false
        },
        "textOpacity_text_house": {
          "value": 1,
          "formula": "0.8",
          "useFormula": true
        },
        "textHoldTime_text_house": {
          "value": 60,
          "formula": "5",
          "useFormula": false
        },
        "textFadeTime_text_house": {
          "value": 2.2,
          "formula": "1",
          "useFormula": false
        },
        "textTypeSpeed_text_house": {
          "value": 200,
          "formula": "60",
          "useFormula": false
        },
        "textEnvironmentDrift_text_house": {
          "value": 0,
          "formula": "0.2 + trend",
          "useFormula": false
        },
        "textInkResolve_text_house": {
          "value": 1,
          "formula": "0.5",
          "useFormula": false
        },
        "textGlow_text_house": {
          "value": 0,
          "formula": "0",
          "useFormula": false
        }
      }
    }
  ],
  "activeIndex": 9,
  "targetIndex": null,
  "transitionStart": 453360.5,
  "transitionDuration": 1000,
  "midiMappings": {
    "pads": {}
  },
  "imported": true
}